setup.py
panoramik_logging/__init__.py
panoramik_logging/formatters.py
panoramik_logging/handlers.py
panoramik_logging.egg-info/PKG-INFO
panoramik_logging.egg-info/SOURCES.txt
panoramik_logging.egg-info/dependency_links.txt
panoramik_logging.egg-info/requires.txt
panoramik_logging.egg-info/top_level.txt