Metadata-Version: 1.1
Name: panoramik-logging
Version: 0.0.2
Summary: Panoramik logging library
Home-page: UNKNOWN
Author: Khusain Orynbaev
Author-email: suhain93@gmail.com
License: MIT
Platform: UNKNOWN
Classifier: Programming Language :: Python :: 2
Classifier: Programming Language :: Python :: 3
Classifier: License :: OSI Approved :: MIT License
Classifier: Operating System :: OS Independent
